{
    "MovieName": "The Beach",
    "Cast": [
        "Leonardo DiCaprio",
        "Daniel York",
        "Patcharawan Patarakijjanon",
        "Virginie Ledoyen",
        "Guillaume Canet",
        "Robert Carlyle",
        "Somboon Phutaroth",
        "Weeratham 'Norman' Wichairaksakui",
        "Sahajak Boonthanakit",
        "Peter Youngblood Hills",
        "Jerry Swindall",
        "Krongthong Thampradith",
        "Apichart Chusakul",
        "Sanya 'Gai' Cheunjit",
        "Kaneung 'Nueng' Kenia"
    ],
    "Director": "Danny Boyle",
    "Genres": [
        "Adventure",
        "Drama",
        "Romance",
        "Thriller"
    ],
    "GrossRevenue": 144056873,
    "Budget": 50000000,
    "NetRevenue": 94056873
}