{
    "MovieName": "Daddy Day Camp",
    "Cast": [
        "Cuba Gooding Jr.",
        "Lochlyn Munro",
        "Richard Gant",
        "Tamala Jones",
        "Paul Rae",
        "Joshua David McLerran",
        "Spencir Bridges",
        "Brian Doyle-Murray",
        "Dallin Boyce",
        "Telise Galanis",
        "Taggart Hurtubise",
        "Molly Jepson",
        "Tad D'Agostino",
        "Tyger Rawlings",
        "Talon G. Ackerman"
    ],
    "Director": "Fred Savage",
    "Genres": [
        "Comedy",
        "Family"
    ],
    "GrossRevenue": 13235267,
    "Budget": 6000000,
    "NetRevenue": 7235267
}