{
    "MovieName": "Ballistic: Ecks vs. Sever",
    "Cast": [
        "Antonio Banderas",
        "Lucy Liu",
        "Gregg Henry",
        "Ray Park",
        "Talisa Soto",
        "Miguel Sandoval",
        "Terry Chen",
        "Roger Cross",
        "Sandrine Holt",
        "Steve Bacic",
        "Aidan Drummond",
        "Eric Breker",
        "Tony Alcantar",
        "David Parker",
        "Josephine Jacob"
    ],
    "Director": "Wych Kaosayananda",
    "Genres": [
        "Action",
        "Crime",
        "Sci-Fi",
        "Thriller"
    ],
    "GrossRevenue": 14294842,
    "Budget": 35000000,
    "NetRevenue": -20705158
}